hipc/__init__.py
hipc/env.py
hipc/job.py
hipc/sync.py
hipc-0.2.1.dist-info/LICENSE
hipc-0.2.1.dist-info/METADATA
hipc-0.2.1.dist-info/WHEEL
hipc-0.2.1.dist-info/RECORD
