Metadata-Version: 2.1
Name: hipc
Version: 0.2.1
Summary: Submission, storage, and extraction on HPC machines.
License: GNU General Public License v3.0
Author: Ryan Park
Requires-Python: >=3.9
Classifier: License :: Other/Proprietary License
Classifier: Programming Language :: Python :: 3
Classifier: Programming Language :: Python :: 3.9
Classifier: Programming Language :: Python :: 3.10
Classifier: Programming Language :: Python :: 3.11
Classifier: Programming Language :: Python :: 3.12
